volutil/__init__.py
volutil/cmdline/__init__.py
volutil/cmdline/vol_cat.py
volutil/cmdline/vol_dice.py
volutil/cmdline/vol_hist.py
volutil/cmdline/vol_info.py
volutil/cmdline/vol_slice.py
volutil/cmdline/vol_stats.py
volutil/cmdline/vol_tr.py
volutil/cmdline/vol_vol.py
volutil-0.3.0.dist-info/COPYING
volutil-0.3.0.dist-info/METADATA
volutil-0.3.0.dist-info/WHEEL
volutil-0.3.0.dist-info/entry_points.txt
volutil-0.3.0.dist-info/top_level.txt
volutil-0.3.0.dist-info/RECORD
