Metadata-Version: 2.1
Name: volutil
Version: 0.3.0
Summary: Neuroimaging volume utilities
Home-page: https://github.com/chaselgrove/volutil
Author: Christian Haselgrove
Author-email: christian.haselgrove@umassmed.edu
Project-URL: Bug Tracker, https://github.com/chaselgrove/volutil/issues
Classifier: Programming Language :: Python :: 3
Classifier: License :: OSI Approved :: BSD License
Classifier: Operating System :: OS Independent
Requires-Python: >=3.7
License-File: COPYING
Requires-Dist: nibabel
Requires-Dist: numpy
Requires-Dist: scipy
Requires-Dist: Pillow
